curses_utils/__init__.py
curses_utils/keys.py
curses_utils/menu.py
curses_utils/number_select.py
curses_utils/wrapper.py
curses_utils-0.0.13.dist-info/METADATA
curses_utils-0.0.13.dist-info/WHEEL
curses_utils-0.0.13.dist-info/top_level.txt
curses_utils-0.0.13.dist-info/RECORD
