Metadata-Version: 2.1
Name: curses-utils
Version: 0.0.13
Summary: Simple curses utilities
Home-page: https://github.com/KinuTheDragon/CursesUtils
Author: Logan Goldberg
Author-email: logangoldberg@hvrsd.org
License: UNKNOWN
Platform: UNKNOWN
Classifier: Programming Language :: Python :: 3
Classifier: Environment :: Console :: Curses
Classifier: Intended Audience :: Developers
Classifier: License :: Freely Distributable
Requires-Python: >=3.7
